aristotlelib/__init__.py
aristotlelib/api_request.py
aristotlelib/date_utils.py
aristotlelib/local_file_utils.py
aristotlelib/project.py
aristotlelib/cli/api_action.py
aristotlelib/cli/controller.py
aristotlelib/cli/prove_from_file.py
aristotlelib/cli/version.py
aristotlelib/tui/__init__.py
aristotlelib/tui/app.py
aristotlelib/tui/menu_options.py
aristotlelib/tui/terminal_size.py
aristotlelib/tui/components/__init__.py
aristotlelib/tui/components/api_key_setup.py
aristotlelib/tui/components/file_path_input.py
aristotlelib/tui/components/history_picker.py
aristotlelib/tui/components/history_table.py
aristotlelib/tui/components/integrated_menu.py
aristotlelib/tui/components/logo.py
aristotlelib/tui/components/message.py
aristotlelib/tui/components/progress.py
aristotlelib/tui/components/terminal_warning.py
aristotlelib/tui/workflows/__init__.py
aristotlelib/tui/workflows/download.py
aristotlelib/tui/workflows/history.py
aristotlelib/tui/workflows/reattach.py
aristotlelib/tui/workflows/unified_solve.py
aristotlelib-0.6.0.dist-info/licenses/LICENSE
aristotlelib-0.6.0.dist-info/METADATA
aristotlelib-0.6.0.dist-info/WHEEL
aristotlelib-0.6.0.dist-info/entry_points.txt
aristotlelib-0.6.0.dist-info/top_level.txt
aristotlelib-0.6.0.dist-info/RECORD
