Metadata-Version: 2.4
Name: aristotlelib
Version: 0.6.0
Summary: Aristotle SDK - Python library for automated theorem proving with Lean
Author: Harmonic
Maintainer: Harmonic
Project-URL: Homepage, https://aristotle.harmonic.fun
Requires-Python: >=3.10
License-File: LICENSE
Requires-Dist: pydantic>=2.0.0
Requires-Dist: httpx>=0.24.0
Requires-Dist: textual>=6.6.0
Provides-Extra: dev
Requires-Dist: textual-dev>=1.8.0; extra == "dev"
Dynamic: license-file
